ai_employee_security/__init__.py
ai_employee_security/approval_verifier.py
ai_employee_security/encryption_utils.py
ai_employee_security/input_validator.py
ai_employee_security/integrity_checker.py
ai_employee_security/path_validator.py
ai_employee_security/secure_logging.py
ai_employee_security_skills-1.0.0.dist-info/licenses/LICENSE
ai_employee_security_skills-1.0.0.dist-info/METADATA
ai_employee_security_skills-1.0.0.dist-info/WHEEL
ai_employee_security_skills-1.0.0.dist-info/top_level.txt
ai_employee_security_skills-1.0.0.dist-info/RECORD
