Metadata-Version: 2.4
Name: ai-employee-security-skills
Version: 1.0.0
Summary: Production-ready security modules: path validation, AES-256-GCM encryption, input sanitization, integrity checking, secure logging, approval verification
Author-email: Umair Aftab <umairaftab@users.noreply.github.com>
License: MIT
Project-URL: Homepage, https://github.com/aftabumair766-lang/AI_Employee_Vault
Project-URL: Repository, https://github.com/aftabumair766-lang/AI_Employee_Vault
Project-URL: Documentation, https://github.com/aftabumair766-lang/AI_Employee_Vault/blob/main/SKILLS.md
Keywords: security,encryption,validation,logging,path-traversal,input-sanitization
Classifier: Development Status :: 5 - Production/Stable
Classifier: Intended Audience :: Developers
Classifier: License :: OSI Approved :: MIT License
Classifier: Programming Language :: Python :: 3
Classifier: Programming Language :: Python :: 3.8
Classifier: Programming Language :: Python :: 3.9
Classifier: Programming Language :: Python :: 3.10
Classifier: Programming Language :: Python :: 3.11
Classifier: Programming Language :: Python :: 3.12
Classifier: Topic :: Security
Classifier: Topic :: Software Development :: Libraries :: Python Modules
Requires-Python: >=3.8
License-File: LICENSE
Requires-Dist: cryptography>=41.0.0
Requires-Dist: zstandard>=0.21.0
Dynamic: license-file
